mathtest/__init__.py
mathtest/add.py
mathtest/sub.py
hello_pkg_pkb2-0.1.3.dist-info/METADATA
hello_pkg_pkb2-0.1.3.dist-info/WHEEL
hello_pkg_pkb2-0.1.3.dist-info/top_level.txt
hello_pkg_pkb2-0.1.3.dist-info/RECORD
