Metadata-Version: 2.4
Name: hello-pkg-pkb2
Version: 0.1.3
Summary: A tiny example package for PyPI
Author-email: Your Name <you@example.com>
License: MIT
Project-URL: Homepage, https://github.com/yourusername/hello-pkg
Project-URL: Bug Tracker, https://github.com/yourusername/hello-pkg/issues
Keywords: hello,example,pypi,tutorial
Classifier: Programming Language :: Python :: 3
Classifier: License :: OSI Approved :: MIT License
Classifier: Operating System :: OS Independent
Requires-Python: >=3.7
